{
	"info": {
		"_postman_id": "f453ada9-abf0-4ef2-8eaf-94544b270785",
		"name": "Osol Task API",
		"description": "Assessment Collection for Task Manager API",
		"schema": "https://schema.getpostman.com/json/collection/v2.0.0/collection.json",
		"_exporter_id": "47715760",
		"_collection_link": "https://mostafaali-php-9353499.postman.co/workspace/Osel~366bcc11-3e37-4022-829c-a8f3a5fe2b3f/collection/47715760-f453ada9-abf0-4ef2-8eaf-94544b270785?action=share&source=collection_link&creator=47715760"
	},
	"item": [
		{
			"name": "Categories",
			"item": [
				{
					"name": "List Categories",
					"request": {
						"auth": {
							"type": "bearer",
							"bearer": {
								"token": "{{token}}"
							}
						},
						"method": "GET",
						"header": [],
						"url": "{{base_url}}/categories"
					},
					"response": []
				},
				{
					"name": "Get Single Category",
					"request": {
						"auth": {
							"type": "bearer",
							"bearer": {
								"token": "{{token}}"
							}
						},
						"method": "GET",
						"header": [],
						"url": "{{base_url}}/categories/1"
					},
					"response": []
				}
			]
		},
		{
			"name": "Tasks",
			"item": [
				{
					"name": "List Tasks (Filtered)",
					"request": {
						"auth": {
							"type": "bearer",
							"bearer": {
								"token": "{{token}}"
							}
						},
						"method": "GET",
						"header": [],
						"url": {
							"raw": "{{base_url}}/tasks?priority=high&completed=0",
							"host": [
								"{{base_url}}"
							],
							"path": [
								"tasks"
							],
							"query": [
								{
									"key": "priority",
									"value": "high"
								},
								{
									"key": "completed",
									"value": "0",
									"description": "// 1 for completed"
								}
							]
						}
					},
					"response": []
				},
				{
					"name": "Create Task",
					"request": {
						"auth": {
							"type": "bearer",
							"bearer": {
								"token": "{{token}}"
							}
						},
						"method": "POST",
						"header": [],
						"body": {
							"mode": "raw",
							"raw": "{\n    \"title\": \"Finish Backend Assessment\",\n    \"description\": \"Write documentation and generate postman collection\",\n    \"priority\": \"high\",\n    \"category_id\": 1,\n    \"due_date\": \"2025-12-30\"\n}",
							"options": {
								"raw": {
									"language": "json"
								}
							}
						},
						"url": "{{base_url}}/tasks"
					},
					"response": []
				},
				{
					"name": "Get Single Task",
					"request": {
						"auth": {
							"type": "bearer",
							"bearer": {
								"token": "{{token}}"
							}
						},
						"method": "GET",
						"header": [],
						"url": "{{base_url}}/tasks/1"
					},
					"response": []
				},
				{
					"name": "Update Task",
					"request": {
						"auth": {
							"type": "bearer",
							"bearer": {
								"token": "{{token}}"
							}
						},
						"method": "PATCH",
						"header": [],
						"body": {
							"mode": "raw",
							"raw": "{\n    \"title\": \"Update: Finished Assessment\",\n    \"completed\": true\n}",
							"options": {
								"raw": {
									"language": "json"
								}
							}
						},
						"url": "{{base_url}}/tasks/1"
					},
					"response": []
				},
				{
					"name": "Delete Task",
					"request": {
						"auth": {
							"type": "bearer",
							"bearer": {
								"token": "{{token}}"
							}
						},
						"method": "DELETE",
						"header": [],
						"url": "{{base_url}}/tasks/1"
					},
					"response": []
				}
			]
		}
	],
	"auth": {
		"type": "bearer",
		"bearer": {}
	},
	"event": [
		{
			"listen": "prerequest",
			"script": {
				"type": "text/javascript",
				"requests": {},
				"exec": [
					""
				]
			}
		},
		{
			"listen": "test",
			"script": {
				"type": "text/javascript",
				"requests": {},
				"exec": [
					""
				]
			}
		}
	],
	"variable": [
		{
			"key": "base_url",
			"value": "http://localhost:8000/api"
		},
		{
			"key": "token",
			"value": "my-secret-token-123"
		}
	]
}
